sintaktikuz/__init__.py
uzsyntactic-0.1.dist-info/LICENSE.txt
uzsyntactic-0.1.dist-info/METADATA
uzsyntactic-0.1.dist-info/WHEEL
uzsyntactic-0.1.dist-info/top_level.txt
uzsyntactic-0.1.dist-info/RECORD
