Metadata-Version: 2.1
Name: uzsyntactic
Version: 0.1
Summary: This package is desgined to help researcher to find syntactic analyse for uzbek language
Author: Alisher Ismailov Shakirovich
Author-email: alisherismailov1991@gmail.com
License: MIT
Classifier: Programming Language :: Python :: 3
Classifier: License :: OSI Approved :: MIT License
Classifier: Operating System :: OS Independent
License-File: LICENSE.txt
